ostrich/__init__.py
ostrich/collector.py
ostrich/constants.py
ostrich/core.py
ostrich/excuses.py
py_ostrich-0.1.1.dist-info/METADATA
py_ostrich-0.1.1.dist-info/WHEEL
py_ostrich-0.1.1.dist-info/RECORD
