Metadata-Version: 2.4
Name: py-ostrich
Version: 0.1.1
Summary: A trolling project turned practical (hopefully) Python decorator for marking and ignoring problems in your code
Project-URL: Homepage, https://github.com/duriantaco/ostrich
Project-URL: Bug Tracker, https://github.com/duriantaco/ostrich/issues
Author-email: oha <aaronoh2003@hotmail.com>
Classifier: Development Status :: 4 - Beta
Classifier: Intended Audience :: Developers
Classifier: License :: OSI Approved :: MIT License
Classifier: Operating System :: OS Independent
Classifier: Programming Language :: Python :: 3
Classifier: Topic :: Software Development :: Documentation
Classifier: Topic :: Software Development :: Libraries :: Python Modules
Requires-Python: >=3.7
